boilersync/__init__.py
boilersync/__main__.py
boilersync/_version.py
boilersync/cli.py
boilersync/cli_helpers.py
boilersync/errors.py
boilersync/interpolation_context.py
boilersync/logging.py
boilersync/names.py
boilersync/paths.py
boilersync/template_processor.py
boilersync/user_settings.py
boilersync/utils.py
boilersync/variable_collector.py
boilersync/commands/__init__.py
boilersync/commands/init.py
boilersync/commands/pull.py
boilersync/commands/push.py
boilersync-1.2.4.dist-info/METADATA
boilersync-1.2.4.dist-info/WHEEL
boilersync-1.2.4.dist-info/entry_points.txt
boilersync-1.2.4.dist-info/RECORD
