Metadata-Version: 2.4
Name: boilersync
Version: 1.2.4
Summary: BoilerSync
Project-URL: Repository, https://github.com/gabemontague/boilersync
Project-URL: Issues, https://github.com/gabemontague/boilersync/issues
Author-email: Gabe Montague <gabemontague@outlook.com>
Classifier: Development Status :: 4 - Beta
Classifier: Environment :: Console
Classifier: Intended Audience :: Developers
Classifier: Operating System :: OS Independent
Classifier: Programming Language :: Python :: 3
Classifier: Programming Language :: Python :: 3.9
Classifier: Topic :: Software Development :: Version Control :: Git
Requires-Python: >=3.9
Requires-Dist: click>=8.2.0
Requires-Dist: gitpython>=3.1.44
Requires-Dist: jinja2>=3.1.6
Provides-Extra: dev
Requires-Dist: pyinstaller>=6.9.0; extra == 'dev'
Requires-Dist: pytest-cov>=6.1.1; extra == 'dev'
Requires-Dist: pytest-mock>=3.14.0; extra == 'dev'
Requires-Dist: pytest>=8.3.5; extra == 'dev'
Requires-Dist: ruff>=0.11.10; extra == 'dev'
